ai_faker/__init__.py
ai_faker/__version__.py
ai_faker/core/__init__.py
ai_faker/core/analyzer.py
ai_faker/core/generator.py
ai_faker/core/llm_interface.py
ai_faker/core/llm_providers/__init__.py
ai_faker/core/llm_providers/base.py
ai_faker/core/llm_providers/gemini_provider.py
ai_faker/core/llm_providers/openai_provider.py
ai_faker/models/__init__.py
ai_faker/models/column_info.py
ai_faker/prompts/__init__.py
ai_faker/prompts/templates.py
ai_faker/tests/__init__.py
ai_faker/utils/__init__.py
ai_faker/utils/string_utils.py
ai_faker/utils/type_mapper.py
sql_ai_faker-1.0.0.dist-info/LICENSE
sql_ai_faker-1.0.0.dist-info/METADATA
sql_ai_faker-1.0.0.dist-info/WHEEL
sql_ai_faker-1.0.0.dist-info/top_level.txt
sql_ai_faker-1.0.0.dist-info/RECORD
