Metadata-Version: 2.2
Name: sql-ai-faker
Version: 1.0.0
Summary: AI-powered fake data generator for SQLAlchemy models using LLMs
Home-page: https://github.com/otabek-olimjonov/ai_faker
Author: Otabek Olimjonov
Author-email: bekdevs01@gmail.com
License: MIT
Project-URL: Bug Reports, https://github.com/otabek-olimjonov/ai_faker/issues
Project-URL: Source, https://github.com/otabek-olimjonov/ai_faker
Keywords: sqlalchemy,faker,ai,llm,testing,database,openai,gemini
Classifier: Development Status :: 3 - Alpha
Classifier: Intended Audience :: Developers
Classifier: License :: OSI Approved :: MIT License
Classifier: Programming Language :: Python :: 3
Classifier: Programming Language :: Python :: 3.8
Classifier: Programming Language :: Python :: 3.9
Classifier: Programming Language :: Python :: 3.10
Classifier: Programming Language :: Python :: 3.11
Classifier: Programming Language :: Python :: 3.12
Requires-Python: >=3.8
License-File: LICENSE
Requires-Dist: sqlalchemy>=1.4.0
Requires-Dist: typing-extensions>=4.0.0
Requires-Dist: python-dotenv>=0.19.0
Provides-Extra: openai
Requires-Dist: openai>=1.0.0; extra == "openai"
Provides-Extra: gemini
Requires-Dist: google-generativeai>=0.3.0; extra == "gemini"
Provides-Extra: all
Requires-Dist: google-generativeai>=0.3.0; extra == "all"
Requires-Dist: openai>=1.0.0; extra == "all"
Dynamic: author
Dynamic: author-email
Dynamic: classifier
Dynamic: description
Dynamic: description-content-type
Dynamic: home-page
Dynamic: keywords
Dynamic: license
Dynamic: project-url
Dynamic: provides-extra
Dynamic: requires-dist
Dynamic: requires-python
Dynamic: summary
